{
  "source_file": "C:\\TD_Projects\\td_builder_workspace\\output\\lossless\\depthMAT_lossless.json",
  "operator_type": "depthMAT",
  "examples": [
    {
      "name": "example1",
      "description": "",
      "operators": [
        {
          "name": "box1",
          "type": "SOP:box",
          "parameters": {
            "sizex": 1.4,
            "sizey": 3,
            "sizez": 0.3
          }
        },
        {
          "name": "cam1",
          "type": "COMP:cam",
          "parameters": {
            "pageindex": 3,
            "tx": 39.0574,
            "ty": -5.91711,
            "tz": 21.7166,
            "rx": -10.8904,
            "ry": -42.3666,
            "rz": -2.25332e-05,
            "px": -52.7909,
            "py": 7.6247,
            "pz": -64.6186,
            "orthowidth": 1,
            "aperture": 44.1
          }
        },
        {
          "name": "geo1",
          "type": "COMP:geo",
          "parameters": {
            "pageindex": 5,
            "instancing": "on",
            "instanceop": "positions",
            "instancetx": "P(0)",
            "instancety": "P(1)",
            "instancetz": "P(2)",
            "material": "phong1"
          }
        },
        {
          "name": "geo2",
          "type": "COMP:geo",
          "parameters": {
            "pageindex": 5,
            "material": "null",
            "drawpriority": 1
          }
        },
        {
          "name": "lfo1",
          "type": "CHOP:lfo",
          "parameters": {
            "frequency": 0.19,
            "timeslice": "on"
          }
        },
        {
          "name": "null",
          "type": "MAT:null",
          "parameters": {}
        },
        {
          "name": "grid1",
          "type": "SOP:grid",
          "parameters": {
            "type": "poly",
            "sizex": 5,
            "sizey": 5.3,
            "rows": 10,
            "cols": 10
          }
        },
        {
          "name": "line1",
          "type": "SOP:line",
          "parameters": {
            "pbz": 30,
            "points": 10
          }
        },
        {
          "name": "math1",
          "type": "CHOP:math",
          "parameters": {
            "pageindex": 2,
            "fromrange1": -1,
            "fromrange2": 1,
            "torange2": 32.5
          }
        },
        {
          "name": "null1",
          "type": "TOP:null",
          "parameters": {}
        },
        {
          "name": "depth1",
          "type": "MAT:depth",
          "parameters": {}
        },
        {
          "name": "light1",
          "type": "COMP:light",
          "parameters": {
            "tx": 44.5027,
            "ty": -15.8883,
            "tz": 34.3084,
            "rx": -22.7133,
            "ry": 318.346,
            "rz": 0.000267386,
            "px": -52.6424,
            "py": 17.2972,
            "pz": -92.1163,
            "orthowidth": 1,
            "aperture": 44.1
          }
        },
        {
          "name": "phong1",
          "type": "MAT:phong",
          "parameters": {
            "diffg": 1,
            "diffb": 0.72549
          }
        },
        {
          "name": "readMe",
          "type": "DAT:text",
          "parameters": {
            "pageindex": 1,
            "defaultreadencoding": "cp1252",
            "language": "text",
            "wordwrap": "on"
          }
        },
        {
          "name": "render1",
          "type": "TOP:render",
          "parameters": {
            "uvunwrapcoordattrib": "uv",
            "resolutionw": 1280,
            "resolutionh": 720
          }
        },
        {
          "name": "comment1",
          "type": "COMP:annotate",
          "parameters": {
            "pageindex": 3,
            "utility": "on",
            "includeinorder": "on"
          }
        },
        {
          "name": "position",
          "type": "CHOP:null",
          "parameters": {}
        },
        {
          "name": "annotate1",
          "type": "COMP:annotate",
          "parameters": {
            "pageindex": 3,
            "includeinorder": "on"
          }
        },
        {
          "name": "positions",
          "type": "SOP:null",
          "parameters": {}
        },
        {
          "name": "wireframe1",
          "type": "MAT:wireframe",
          "parameters": {
            "wireframemode": "topology",
            "linewidth": 4.22
          }
        },
        {
          "name": "switchMaterial",
          "type": "MAT:switch",
          "parameters": {
            "index": 1
          }
        }
      ],
      "connections": [
        {
          "from": "switchMaterial",
          "to": "null",
          "to_input": "0"
        },
        {
          "from": "lfo1",
          "to": "math1",
          "to_input": "0"
        },
        {
          "from": "render1",
          "to": "null1",
          "to_input": "0"
        },
        {
          "from": "math1",
          "to": "position",
          "to_input": "0"
        },
        {
          "from": "line1",
          "to": "positions",
          "to_input": "0"
        },
        {
          "from": "depth1",
          "to": "switchMaterial",
          "to_input": "0"
        },
        {
          "from": "wireframe1",
          "to": "switchMaterial",
          "to_input": "1"
        }
      ],
      "network_pattern": {
        "operator_count": 21,
        "connection_count": 7,
        "operator_types": {
          "SOP:box": 1,
          "COMP:cam": 1,
          "COMP:geo": 2,
          "CHOP:lfo": 1,
          "MAT:null": 1,
          "SOP:grid": 1,
          "SOP:line": 1,
          "CHOP:math": 1,
          "TOP:null": 1,
          "MAT:depth": 1,
          "COMP:light": 1,
          "MAT:phong": 1,
          "DAT:text": 1,
          "TOP:render": 1,
          "COMP:annotate": 2,
          "CHOP:null": 1,
          "SOP:null": 1,
          "MAT:wireframe": 1,
          "MAT:switch": 1
        },
        "has_parallel_paths": false,
        "has_feedback_loops": false,
        "max_chain_length": 3
      }
    }
  ]
}