{
  "source_file": "C:\\TD_Projects\\td_builder_workspace\\output\\lossless\\limitCHOP_lossless.json",
  "operator_type": "limitCHOP",
  "examples": [
    {
      "name": "example1",
      "description": "",
      "operators": [
        {
          "name": "noise2",
          "type": "CHOP:noise",
          "parameters": {
            "pageindex": 3,
            "seed": 1.3,
            "period": 2,
            "end": 2
          }
        },
        {
          "name": "readMe",
          "type": "DAT:text",
          "parameters": {
            "defaultreadencoding": "cp1252",
            "language": "text",
            "wordwrap": "on"
          }
        },
        {
          "name": "limit_index",
          "type": "CHOP:limit",
          "parameters": {
            "pageindex": 1,
            "quantindex": "relstart",
            "istep": 0.4
          }
        },
        {
          "name": "limit_quantize_value",
          "type": "CHOP:limit",
          "parameters": {
            "pageindex": 1,
            "quantvalue": "floor"
          }
        }
      ],
      "connections": [
        {
          "from": "noise2",
          "to": "limit_index",
          "to_input": "0"
        },
        {
          "from": "noise2",
          "to": "limit_quantize_value",
          "to_input": "0"
        }
      ],
      "network_pattern": {
        "operator_count": 4,
        "connection_count": 2,
        "operator_types": {
          "CHOP:noise": 1,
          "DAT:text": 1,
          "CHOP:limit": 2
        },
        "has_parallel_paths": true,
        "has_feedback_loops": false,
        "max_chain_length": 2
      }
    },
    {
      "name": "example2",
      "description": "",
      "operators": [
        {
          "name": "lfo1",
          "type": "CHOP:lfo",
          "parameters": {
            "frequency": 0.25,
            "timeslice": "on"
          }
        },
        {
          "name": "readMe",
          "type": "DAT:text",
          "parameters": {
            "defaultreadencoding": "cp1252",
            "language": "text",
            "wordwrap": "on"
          }
        },
        {
          "name": "trail1",
          "type": "CHOP:trail",
          "parameters": {
            "timeslice": "on"
          }
        },
        {
          "name": "limit_clamp",
          "type": "CHOP:limit",
          "parameters": {
            "type": "clamp",
            "min": -0.5,
            "max": 0.5
          }
        }
      ],
      "connections": [
        {
          "from": "limit_clamp",
          "to": "trail1",
          "to_input": "0"
        },
        {
          "from": "lfo1",
          "to": "limit_clamp",
          "to_input": "0"
        }
      ],
      "network_pattern": {
        "operator_count": 4,
        "connection_count": 2,
        "operator_types": {
          "CHOP:lfo": 1,
          "DAT:text": 1,
          "CHOP:trail": 1,
          "CHOP:limit": 1
        },
        "has_parallel_paths": false,
        "has_feedback_loops": false,
        "max_chain_length": 3
      }
    },
    {
      "name": "example3",
      "description": "",
      "operators": [
        {
          "name": "readMe",
          "type": "DAT:text",
          "parameters": {
            "defaultreadencoding": "cp1252",
            "language": "text",
            "wordwrap": "on"
          }
        },
        {
          "name": "speed1",
          "type": "CHOP:speed",
          "parameters": {
            "timeslice": "on"
          }
        },
        {
          "name": "trail2",
          "type": "CHOP:trail",
          "parameters": {
            "timeslice": "on"
          }
        },
        {
          "name": "constant1",
          "type": "CHOP:constant",
          "parameters": {
            "const0value": 0.5
          }
        },
        {
          "name": "limit_loop",
          "type": "CHOP:limit",
          "parameters": {
            "type": "loop",
            "max": 2
          }
        }
      ],
      "connections": [
        {
          "from": "constant1",
          "to": "speed1",
          "to_input": "0"
        },
        {
          "from": "limit_loop",
          "to": "trail2",
          "to_input": "0"
        },
        {
          "from": "speed1",
          "to": "limit_loop",
          "to_input": "0"
        }
      ],
      "network_pattern": {
        "operator_count": 5,
        "connection_count": 3,
        "operator_types": {
          "DAT:text": 1,
          "CHOP:speed": 1,
          "CHOP:trail": 1,
          "CHOP:constant": 1,
          "CHOP:limit": 1
        },
        "has_parallel_paths": false,
        "has_feedback_loops": false,
        "max_chain_length": 4
      }
    },
    {
      "name": "example4",
      "description": "",
      "operators": [
        {
          "name": "readMe",
          "type": "DAT:text",
          "parameters": {
            "defaultreadencoding": "cp1252",
            "language": "text",
            "wordwrap": "on"
          }
        },
        {
          "name": "speed2",
          "type": "CHOP:speed",
          "parameters": {
            "timeslice": "on"
          }
        },
        {
          "name": "trail3",
          "type": "CHOP:trail",
          "parameters": {
            "timeslice": "on"
          }
        },
        {
          "name": "constant2",
          "type": "CHOP:constant",
          "parameters": {
            "const0value": 0.5
          }
        },
        {
          "name": "limit_zigzag",
          "type": "CHOP:limit",
          "parameters": {
            "type": "zigzag",
            "max": 2
          }
        }
      ],
      "connections": [
        {
          "from": "constant2",
          "to": "speed2",
          "to_input": "0"
        },
        {
          "from": "limit_zigzag",
          "to": "trail3",
          "to_input": "0"
        },
        {
          "from": "speed2",
          "to": "limit_zigzag",
          "to_input": "0"
        }
      ],
      "network_pattern": {
        "operator_count": 5,
        "connection_count": 3,
        "operator_types": {
          "DAT:text": 1,
          "CHOP:speed": 1,
          "CHOP:trail": 1,
          "CHOP:constant": 1,
          "CHOP:limit": 1
        },
        "has_parallel_paths": false,
        "has_feedback_loops": false,
        "max_chain_length": 4
      }
    },
    {
      "name": "example5",
      "description": "",
      "operators": [
        {
          "name": "lfo2",
          "type": "CHOP:lfo",
          "parameters": {
            "frequency": 0.25,
            "timeslice": "on"
          }
        },
        {
          "name": "readMe",
          "type": "DAT:text",
          "parameters": {
            "defaultreadencoding": "cp1252",
            "language": "text",
            "wordwrap": "on"
          }
        },
        {
          "name": "trail4",
          "type": "CHOP:trail",
          "parameters": {
            "timeslice": "on"
          }
        },
        {
          "name": "limit_positive",
          "type": "CHOP:limit",
          "parameters": {
            "positive": "on"
          }
        }
      ],
      "connections": [
        {
          "from": "limit_positive",
          "to": "trail4",
          "to_input": "0"
        },
        {
          "from": "lfo2",
          "to": "limit_positive",
          "to_input": "0"
        }
      ],
      "network_pattern": {
        "operator_count": 4,
        "connection_count": 2,
        "operator_types": {
          "CHOP:lfo": 1,
          "DAT:text": 1,
          "CHOP:trail": 1,
          "CHOP:limit": 1
        },
        "has_parallel_paths": false,
        "has_feedback_loops": false,
        "max_chain_length": 3
      }
    },
    {
      "name": "example6",
      "description": "",
      "operators": [
        {
          "name": "noise1",
          "type": "CHOP:noise",
          "parameters": {
            "amp": 10
          }
        },
        {
          "name": "readMe",
          "type": "DAT:text",
          "parameters": {
            "defaultreadencoding": "cp1252",
            "language": "text",
            "wordwrap": "on"
          }
        },
        {
          "name": "trail5",
          "type": "CHOP:trail",
          "parameters": {
            "timeslice": "on"
          }
        },
        {
          "name": "limit_normalize",
          "type": "CHOP:limit",
          "parameters": {
            "norm": "on"
          }
        }
      ],
      "connections": [
        {
          "from": "limit_normalize",
          "to": "trail5",
          "to_input": "0"
        },
        {
          "from": "noise1",
          "to": "limit_normalize",
          "to_input": "0"
        }
      ],
      "network_pattern": {
        "operator_count": 4,
        "connection_count": 2,
        "operator_types": {
          "CHOP:noise": 1,
          "DAT:text": 1,
          "CHOP:trail": 1,
          "CHOP:limit": 1
        },
        "has_parallel_paths": false,
        "has_feedback_loops": false,
        "max_chain_length": 3
      }
    },
    {
      "name": "example7",
      "description": "",
      "operators": [
        {
          "name": "lfo4",
          "type": "CHOP:lfo",
          "parameters": {
            "timeslice": "on"
          }
        },
        {
          "name": "readMe",
          "type": "DAT:text",
          "parameters": {
            "defaultreadencoding": "cp1252",
            "language": "text",
            "wordwrap": "on"
          }
        },
        {
          "name": "trail6",
          "type": "CHOP:trail",
          "parameters": {
            "timeslice": "on"
          }
        },
        {
          "name": "trail7",
          "type": "CHOP:trail",
          "parameters": {
            "timeslice": "on"
          }
        },
        {
          "name": "limit_quantize",
          "type": "CHOP:limit",
          "parameters": {
            "pageindex": 1,
            "quantvalue": "round",
            "vstep": 1
          }
        },
        {
          "name": "limit_quantize1",
          "type": "CHOP:limit",
          "parameters": {
            "pageindex": 1,
            "quantvalue": "round",
            "vstep": 0.5,
            "voffset": 0.5
          }
        }
      ],
      "connections": [
        {
          "from": "limit_quantize",
          "to": "trail6",
          "to_input": "0"
        },
        {
          "from": "limit_quantize1",
          "to": "trail7",
          "to_input": "0"
        },
        {
          "from": "lfo4",
          "to": "limit_quantize",
          "to_input": "0"
        },
        {
          "from": "lfo4",
          "to": "limit_quantize1",
          "to_input": "0"
        }
      ],
      "network_pattern": {
        "operator_count": 6,
        "connection_count": 4,
        "operator_types": {
          "CHOP:lfo": 1,
          "DAT:text": 1,
          "CHOP:trail": 2,
          "CHOP:limit": 2
        },
        "has_parallel_paths": true,
        "has_feedback_loops": false,
        "max_chain_length": 3
      }
    },
    {
      "name": "example8",
      "description": "",
      "operators": [
        {
          "name": "lfo1",
          "type": "CHOP:lfo",
          "parameters": {
            "wavetype": "tri",
            "frequency": 0.1,
            "offset": 0.5,
            "amp": 0.5,
            "timeslice": "on"
          }
        },
        {
          "name": "grid1",
          "type": "SOP:grid",
          "parameters": {
            "sizex": 100,
            "sizey": 100,
            "reverseanchors": "on"
          }
        },
        {
          "name": "math1",
          "type": "CHOP:math",
          "parameters": {
            "chopop": "add",
            "match": "name"
          }
        },
        {
          "name": "math2",
          "type": "CHOP:math",
          "parameters": {
            "pageindex": 2,
            "torange1": -200,
            "torange2": 200
          }
        },
        {
          "name": "math3",
          "type": "CHOP:math",
          "parameters": {
            "chopop": "add",
            "match": "name",
            "align": "stretch1"
          }
        },
        {
          "name": "math4",
          "type": "CHOP:math",
          "parameters": {
            "chopop": "add"
          }
        },
        {
          "name": "null1",
          "type": "CHOP:null",
          "parameters": {}
        },
        {
          "name": "limit1",
          "type": "CHOP:limit",
          "parameters": {
            "type": "loop",
            "min": -50,
            "max": 50,
            "scope": "tx"
          }
        },
        {
          "name": "noise1",
          "type": "CHOP:noise",
          "parameters": {
            "type": "random",
            "amp": 2,
            "channelname": "\"tx ty\""
          }
        },
        {
          "name": "readMe",
          "type": "DAT:text",
          "parameters": {
            "defaultreadencoding": "cp1252",
            "language": "text",
            "wordwrap": "on"
          }
        },
        {
          "name": "sopto1",
          "type": "CHOP:sopto",
          "parameters": {
            "sop": "grid1",
            "custom": "on",
            "attribscope": "P",
            "renamescope": "\"tx ty tz\"",
            "exportmethod": "datname"
          }
        },
        {
          "name": "chopto1",
          "type": "SOP:chopto",
          "parameters": {
            "chop": "math1"
          }
        },
        {
          "name": "chopto2",
          "type": "SOP:chopto",
          "parameters": {
            "chop": "limit1"
          }
        },
        {
          "name": "delete1",
          "type": "SOP:delete",
          "parameters": {
            "keeppoints": "on"
          }
        },
        {
          "name": "rename1",
          "type": "CHOP:rename",
          "parameters": {
            "renameto": "tx"
          }
        },
        {
          "name": "cameraPos",
          "type": "COMP:slider",
          "parameters": {
            "value0": 0.292929,
            "w": 100,
            "h": 20,
            "bgalpha": 1,
            "topsmoothness": "mipmap",
            "borderar": 0.43,
            "borderag": 0.43,
            "borderab": 0.43,
            "leftborder": "bordera",
            "rightborder": "bordera",
            "bottomborder": "bordera",
            "topborder": "bordera"
          }
        }
      ],
      "connections": [
        {
          "from": "sopto1",
          "to": "math1",
          "to_input": "0"
        },
        {
          "from": "noise1",
          "to": "math1",
          "to_input": "1"
        },
        {
          "from": "rename1",
          "to": "math2",
          "to_input": "0"
        },
        {
          "from": "math1",
          "to": "math3",
          "to_input": "0"
        },
        {
          "from": "math2",
          "to": "math3",
          "to_input": "1"
        },
        {
          "from": "lfo1",
          "to": "math4",
          "to_input": "0"
        },
        {
          "from": "null1",
          "to": "math4",
          "to_input": "1"
        },
        {
          "from": "cameraPos/out1",
          "to": "null1",
          "to_input": "0"
        },
        {
          "from": "math3",
          "to": "limit1",
          "to_input": "0"
        },
        {
          "from": "sopto1",
          "to": "noise1",
          "to_input": "0"
        },
        {
          "from": "delete1",
          "to": "chopto1",
          "to_input": "0"
        },
        {
          "from": "delete1",
          "to": "chopto2",
          "to_input": "0"
        },
        {
          "from": "grid1",
          "to": "delete1",
          "to_input": "0"
        },
        {
          "from": "math4",
          "to": "rename1",
          "to_input": "0"
        }
      ],
      "network_pattern": {
        "operator_count": 16,
        "connection_count": 14,
        "operator_types": {
          "CHOP:lfo": 1,
          "SOP:grid": 1,
          "CHOP:math": 4,
          "CHOP:null": 1,
          "CHOP:limit": 1,
          "CHOP:noise": 1,
          "DAT:text": 1,
          "CHOP:sopto": 1,
          "SOP:chopto": 2,
          "SOP:delete": 1,
          "CHOP:rename": 1,
          "COMP:slider": 1
        },
        "has_parallel_paths": true,
        "has_feedback_loops": false,
        "max_chain_length": 6
      }
    }
  ]
}