{
  "source_file": "C:\\TD_Projects\\td_builder_workspace\\output\\lossless\\pbrMAT_lossless.json",
  "operator_type": "pbrMAT",
  "examples": [
    {
      "name": "example1",
      "description": "",
      "operators": [
        {
          "name": "sun",
          "type": "COMP:environment",
          "parameters": {
            "dimmer": 0.5,
            "envlightmap": "moviefilein1"
          }
        },
        {
          "name": "cam1",
          "type": "COMP:cam",
          "parameters": {
            "tx": -0.0658567,
            "ty": 1.38252,
            "tz": 6.07687,
            "rx": -28.0544,
            "ry": -0.406667,
            "rz": -0.873279,
            "px": 0.0658566,
            "py": -2.08252,
            "pz": -3.07687,
            "orthowidth": 1,
            "aperture": 44.1,
            "winrollpivot": "legacy"
          }
        },
        {
          "name": "geo1",
          "type": "COMP:geo",
          "parameters": {
            "rz": 30,
            "material": "pbr1"
          }
        },
        {
          "name": "pbr1",
          "type": "MAT:pbr",
          "parameters": {
            "substance": "substance1",
            "bumpscale": 3,
            "legacyalphabehavior": "on"
          }
        },
        {
          "name": "math1",
          "type": "CHOP:math",
          "parameters": {
            "pageindex": 1,
            "gain": 4,
            "exporttable": "math1_export"
          }
        },
        {
          "name": "light1",
          "type": "COMP:light",
          "parameters": {
            "pageindex": 2,
            "tx": 3.39721,
            "ty": 3.32923,
            "tz": 10,
            "rx": -22.4535,
            "ry": 20.8303,
            "rz": -7.51474,
            "px": -3.39721,
            "py": -3.32924,
            "orthowidth": 1,
            "aperture": 44.1
          }
        },
        {
          "name": "readMe",
          "type": "DAT:text",
          "parameters": {
            "pageindex": 1,
            "defaultreadencoding": "cp1252",
            "language": "text",
            "wordwrap": "on"
          }
        },
        {
          "name": "render1",
          "type": "TOP:render",
          "parameters": {
            "uvunwrapcoordattrib": "uv",
            "resolutionw": 1280,
            "resolutionh": 720
          }
        },
        {
          "name": "constant1",
          "type": "CHOP:constant",
          "parameters": {}
        },
        {
          "name": "substance1",
          "type": "TOP:substance",
          "parameters": {
            "graph": "graph1",
            "resolutionw": 1024,
            "resolutionh": 1024
          }
        },
        {
          "name": "math1_export",
          "type": "DAT:table",
          "parameters": {
            "defaultreadencoding": "cp1252",
            "language": "text"
          }
        },
        {
          "name": "moviefilein1",
          "type": "TOP:moviefilein",
          "parameters": {}
        }
      ],
      "connections": [
        {
          "from": "constant1",
          "to": "math1",
          "to_input": "0"
        }
      ],
      "network_pattern": {
        "operator_count": 12,
        "connection_count": 1,
        "operator_types": {
          "COMP:environment": 1,
          "COMP:cam": 1,
          "COMP:geo": 1,
          "MAT:pbr": 1,
          "CHOP:math": 1,
          "COMP:light": 1,
          "DAT:text": 1,
          "TOP:render": 1,
          "CHOP:constant": 1,
          "TOP:substance": 1,
          "DAT:table": 1,
          "TOP:moviefilein": 1
        },
        "has_parallel_paths": false,
        "has_feedback_loops": false,
        "max_chain_length": 2
      }
    },
    {
      "name": "example2",
      "description": "",
      "operators": [
        {
          "name": "cam1",
          "type": "COMP:cam",
          "parameters": {
            "tx": -0.0658567,
            "ty": 1.38252,
            "tz": 6.07687,
            "rx": -28.0544,
            "ry": -0.406667,
            "rz": -0.873279,
            "px": 0.0658566,
            "py": -2.08252,
            "pz": -3.07687,
            "orthowidth": 1,
            "aperture": 44.1,
            "winrollpivot": "legacy"
          }
        },
        {
          "name": "geo1",
          "type": "COMP:geo",
          "parameters": {
            "material": "pbr1"
          }
        },
        {
          "name": "pbr1",
          "type": "MAT:pbr",
          "parameters": {
            "pageindex": 1,
            "metallicmap": "metallic",
            "roughnessmap": "roughness",
            "ambientocclusionmap": "amboccl",
            "normalmap": "normal",
            "bumpscale": 3,
            "legacyalphabehavior": "on"
          }
        },
        {
          "name": "level1",
          "type": "TOP:level",
          "parameters": {
            "pageindex": 2,
            "clampinput": "clamp",
            "highg": 0.525,
            "highb": 0.36
          }
        },
        {
          "name": "light1",
          "type": "COMP:light",
          "parameters": {
            "pageindex": 2,
            "tx": 3.39721,
            "ty": 3.32923,
            "tz": 10,
            "rx": -22.4535,
            "ry": 20.8303,
            "rz": -7.51474,
            "px": -3.39721,
            "py": -3.32924,
            "dimmer": 2,
            "orthowidth": 1,
            "aperture": 44.1
          }
        },
        {
          "name": "normal",
          "type": "TOP:subselect",
          "parameters": {
            "substance": "substance1",
            "output": "normal"
          }
        },
        {
          "name": "readMe",
          "type": "DAT:text",
          "parameters": {
            "pageindex": 1,
            "defaultreadencoding": "cp1252",
            "language": "text",
            "wordwrap": "on"
          }
        },
        {
          "name": "amboccl",
          "type": "TOP:subselect",
          "parameters": {
            "substance": "substance1",
            "output": "ambient_occlusion"
          }
        },
        {
          "name": "hsvadj1",
          "type": "TOP:hsvadj",
          "parameters": {
            "valuerange": 0.285,
            "saturationmult": 0.18,
            "valuemult": 1.25
          }
        },
        {
          "name": "render1",
          "type": "TOP:render",
          "parameters": {
            "uvunwrapcoordattrib": "uv",
            "resolutionw": 1280,
            "resolutionh": 720
          }
        },
        {
          "name": "metallic",
          "type": "TOP:subselect",
          "parameters": {
            "substance": "substance1",
            "output": "metallic"
          }
        },
        {
          "name": "basecolor",
          "type": "TOP:subselect",
          "parameters": {
            "substance": "substance1",
            "output": "basecolor"
          }
        },
        {
          "name": "roughness",
          "type": "TOP:subselect",
          "parameters": {
            "substance": "substance1",
            "output": "roughness"
          }
        },
        {
          "name": "substance1",
          "type": "TOP:substance",
          "parameters": {
            "graph": "graph1",
            "resolutionw": 1024,
            "resolutionh": 1024
          }
        }
      ],
      "connections": [
        {
          "from": "basecolor",
          "to": "level1",
          "to_input": "0"
        },
        {
          "from": "level1",
          "to": "hsvadj1",
          "to_input": "0"
        }
      ],
      "network_pattern": {
        "operator_count": 14,
        "connection_count": 2,
        "operator_types": {
          "COMP:cam": 1,
          "COMP:geo": 1,
          "MAT:pbr": 1,
          "TOP:level": 1,
          "COMP:light": 1,
          "TOP:subselect": 5,
          "DAT:text": 1,
          "TOP:hsvadj": 1,
          "TOP:render": 1,
          "TOP:substance": 1
        },
        "has_parallel_paths": false,
        "has_feedback_loops": false,
        "max_chain_length": 3
      }
    },
    {
      "name": "example3",
      "description": "",
      "operators": [
        {
          "name": "cam1",
          "type": "COMP:cam",
          "parameters": {
            "tx": 2.20757,
            "ty": 3.62407,
            "tz": 11.4027,
            "rx": -77.4542,
            "ry": 39.312,
            "rz": -44.0199,
            "px": -2.20757,
            "py": -3.62407,
            "pz": -6.40273,
            "orthowidth": 1,
            "aperture": 44.1,
            "winrollpivot": "legacy"
          }
        },
        {
          "name": "geo1",
          "type": "COMP:geo",
          "parameters": {
            "pageindex": 2,
            "rz": 45,
            "instancing": "on",
            "instanceop": "rename1",
            "instancetx": "tx",
            "instancesx": "s",
            "instancesy": "s",
            "instancesz": "s",
            "material": "pbr1"
          }
        },
        {
          "name": "geo2",
          "type": "COMP:geo",
          "parameters": {
            "tx": -2,
            "tz": 1,
            "sx": 0.6,
            "sy": 0.6,
            "sz": 0.6,
            "material": "pbr2"
          }
        },
        {
          "name": "lfo1",
          "type": "CHOP:lfo",
          "parameters": {
            "wavetype": "normal",
            "frequency": 0.1,
            "timeslice": "on"
          }
        },
        {
          "name": "pbr1",
          "type": "MAT:pbr",
          "parameters": {
            "pageindex": 4,
            "specularlevel": 0.5,
            "roughness": 0.5,
            "emitr": 1,
            "emitg": 1,
            "emitb": 1,
            "substance": "substance1",
            "normalmap": "normal1",
            "bumpscale": 3,
            "emitmap": "moviefilein1",
            "alphaside": 1,
            "rolloff": 10,
            "rimlight0enable": "on",
            "rimlight0center": 48,
            "legacyalphabehavior": "on"
          }
        },
        {
          "name": "pbr2",
          "type": "MAT:pbr",
          "parameters": {
            "pageindex": 4,
            "metallic": 0.462,
            "roughness": 0.5,
            "substance": "substance2",
            "legacyalphabehavior": "on"
          }
        },
        {
          "name": "math1",
          "type": "CHOP:math",
          "parameters": {
            "pageindex": 1,
            "gain": 10,
            "exporttable": "math1_export"
          }
        },
        {
          "name": "wave2",
          "type": "CHOP:wave",
          "parameters": {
            "ramp": 3,
            "startunit": "samples",
            "end": 1,
            "endunit": "samples"
          }
        },
        {
          "name": "wave3",
          "type": "CHOP:wave",
          "parameters": {
            "offset": 2,
            "amp": 0.4,
            "ramp": -1,
            "startunit": "samples",
            "end": 1,
            "endunit": "samples"
          }
        },
        {
          "name": "light1",
          "type": "COMP:light",
          "parameters": {
            "pageindex": 2,
            "tz": 10
          }
        },
        {
          "name": "light2",
          "type": "COMP:light",
          "parameters": {
            "pageindex": 2,
            "tx": 12.6382,
            "ty": 5.65964,
            "tz": 19.6152,
            "rx": -68.9329,
            "ry": 66.6522,
            "rz": -51.5368,
            "px": -12.6382,
            "py": -5.65964,
            "pz": -9.61515,
            "orthowidth": 1,
            "aperture": 44.1
          }
        },
        {
          "name": "merge1",
          "type": "CHOP:merge",
          "parameters": {}
        },
        {
          "name": "readMe",
          "type": "DAT:text",
          "parameters": {
            "pageindex": 1,
            "defaultreadencoding": "cp1252",
            "language": "text",
            "wordwrap": "on"
          }
        },
        {
          "name": "normal1",
          "type": "TOP:normal",
          "parameters": {}
        },
        {
          "name": "rename1",
          "type": "CHOP:rename",
          "parameters": {
            "renameto": "\"tx s\""
          }
        },
        {
          "name": "render1",
          "type": "TOP:render",
          "parameters": {
            "pageindex": 1,
            "uvunwrapcoordattrib": "uv",
            "resolutionw": 1280,
            "resolutionh": 720
          }
        },
        {
          "name": "constant1",
          "type": "CHOP:constant",
          "parameters": {}
        },
        {
          "name": "substance1",
          "type": "TOP:substance",
          "parameters": {
            "pageindex": 1,
            "graph": "graph2",
            "resolutionw": 512,
            "resolutionh": 512
          }
        },
        {
          "name": "substance2",
          "type": "TOP:substance",
          "parameters": {
            "graph": "graph6"
          }
        },
        {
          "name": "emit_render",
          "type": "TOP:renderselect",
          "parameters": {
            "top": "render1",
            "bufferindex": 5
          }
        },
        {
          "name": "math1_export",
          "type": "DAT:table",
          "parameters": {
            "defaultreadencoding": "cp1252",
            "language": "text"
          }
        },
        {
          "name": "moviefilein1",
          "type": "TOP:moviefilein",
          "parameters": {}
        },
        {
          "name": "normal_render",
          "type": "TOP:renderselect",
          "parameters": {
            "top": "render1",
            "bufferindex": 4
          }
        },
        {
          "name": "amboccl_render",
          "type": "TOP:renderselect",
          "parameters": {
            "top": "render1",
            "bufferindex": 3
          }
        },
        {
          "name": "metallic_render",
          "type": "TOP:renderselect",
          "parameters": {
            "top": "render1",
            "bufferindex": 2
          }
        },
        {
          "name": "roughness_render",
          "type": "TOP:renderselect",
          "parameters": {
            "top": "render1",
            "bufferindex": 1
          }
        }
      ],
      "connections": [
        {
          "from": "constant1",
          "to": "math1",
          "to_input": "0"
        },
        {
          "from": "wave2",
          "to": "merge1",
          "to_input": "0"
        },
        {
          "from": "wave3",
          "to": "merge1",
          "to_input": "1"
        },
        {
          "from": "moviefilein1",
          "to": "normal1",
          "to_input": "0"
        },
        {
          "from": "merge1",
          "to": "rename1",
          "to_input": "0"
        }
      ],
      "network_pattern": {
        "operator_count": 26,
        "connection_count": 5,
        "operator_types": {
          "COMP:cam": 1,
          "COMP:geo": 2,
          "CHOP:lfo": 1,
          "MAT:pbr": 2,
          "CHOP:math": 1,
          "CHOP:wave": 2,
          "COMP:light": 2,
          "CHOP:merge": 1,
          "DAT:text": 1,
          "TOP:normal": 1,
          "CHOP:rename": 1,
          "TOP:render": 1,
          "CHOP:constant": 1,
          "TOP:substance": 2,
          "TOP:renderselect": 5,
          "DAT:table": 1,
          "TOP:moviefilein": 1
        },
        "has_parallel_paths": false,
        "has_feedback_loops": false,
        "max_chain_length": 3
      }
    },
    {
      "name": "example4",
      "description": "",
      "operators": [
        {
          "name": "cam1",
          "type": "COMP:cam",
          "parameters": {
            "tx": -3.28124e-05,
            "ty": 0.0701644,
            "tz": 5.08527,
            "px": 0.347282,
            "py": 0.674068,
            "pz": -1.74407,
            "orthowidth": 1,
            "aperture": 44.1,
            "far": 3470110.0,
            "winrollpivot": "legacy"
          }
        },
        {
          "name": "height",
          "type": "TOP:subselect",
          "parameters": {
            "substance": "substance1",
            "output": "height"
          }
        },
        {
          "name": "light1",
          "type": "COMP:light",
          "parameters": {
            "pageindex": 2,
            "tx": 3.39721,
            "ty": 3.32923,
            "tz": 10,
            "rx": -22.4535,
            "ry": 20.8303,
            "rz": -7.51474,
            "px": -3.39721,
            "py": -3.32924,
            "dimmer": 1.8,
            "orthowidth": 1,
            "aperture": 44.1
          }
        },
        {
          "name": "normal",
          "type": "TOP:subselect",
          "parameters": {
            "substance": "substance1",
            "output": "normal"
          }
        },
        {
          "name": "readMe",
          "type": "DAT:text",
          "parameters": {
            "pageindex": 1,
            "defaultreadencoding": "cp1252",
            "language": "text",
            "wordwrap": "on"
          }
        },
        {
          "name": "amboccl",
          "type": "TOP:subselect",
          "parameters": {
            "substance": "substance1",
            "output": "ambient_occlusion"
          }
        },
        {
          "name": "render1",
          "type": "TOP:render",
          "parameters": {
            "uvunwrapcoordattrib": "uv",
            "resolutionw": 1280,
            "resolutionh": 720
          }
        },
        {
          "name": "metallic",
          "type": "TOP:subselect",
          "parameters": {
            "substance": "substance1",
            "output": "metallic"
          }
        },
        {
          "name": "basecolor",
          "type": "TOP:subselect",
          "parameters": {
            "substance": "substance1",
            "output": "basecolor"
          }
        },
        {
          "name": "no_height",
          "type": "MAT:pbr",
          "parameters": {
            "pageindex": 1,
            "metallicmap": "metallic",
            "roughnessmap": "roughness",
            "ambientocclusionmap": "amboccl",
            "normalmap": "normal",
            "bumpscale": 2.5,
            "heightmap": "height",
            "legacyalphabehavior": "on"
          }
        },
        {
          "name": "roughness",
          "type": "TOP:subselect",
          "parameters": {
            "substance": "substance1",
            "output": "roughness"
          }
        },
        {
          "name": "substance1",
          "type": "TOP:substance",
          "parameters": {
            "pageindex": 1,
            "graph": "graph1",
            "resolutionw": 1024,
            "resolutionh": 1024
          }
        },
        {
          "name": "using_height",
          "type": "MAT:pbr",
          "parameters": {
            "pageindex": 1,
            "metallicmap": "metallic",
            "roughnessmap": "roughness",
            "ambientocclusionmap": "amboccl",
            "normalmap": "normal",
            "bumpscale": 2.5,
            "heightmapenable": "on",
            "heightmap": "height",
            "parallaxscale": 2,
            "parallaxocclusion": "on",
            "legacyalphabehavior": "on"
          }
        },
        {
          "name": "no_height_geo",
          "type": "COMP:geo",
          "parameters": {
            "tx": -1.1,
            "material": "no_height"
          }
        },
        {
          "name": "using_height_geo",
          "type": "COMP:geo",
          "parameters": {
            "tx": 1.1,
            "material": "using_height"
          }
        }
      ],
      "connections": [],
      "network_pattern": {
        "operator_count": 15,
        "connection_count": 0,
        "operator_types": {
          "COMP:cam": 1,
          "TOP:subselect": 6,
          "COMP:light": 1,
          "DAT:text": 1,
          "TOP:render": 1,
          "MAT:pbr": 2,
          "TOP:substance": 1,
          "COMP:geo": 2
        },
        "has_parallel_paths": false,
        "has_feedback_loops": false,
        "max_chain_length": 1
      }
    }
  ]
}