{
  "source_file": "C:\\TD_Projects\\kb_pipeline\\data\\snippets\\lossless_pop\\pointfileinPOP_lossless.json",
  "operator_type": "pointfileinPOP",
  "examples": [
    {
      "name": "example1",
      "description": "",
      "operators": [
        {
          "name": "readMe",
          "type": "DAT:text",
          "parameters": {
            "defaultreadencoding": "cp1252",
            "language": "text",
            "wordwrap": "on"
          }
        },
        {
          "name": "delete1",
          "type": "POP:delete",
          "parameters": {
            "pageindex": 2,
            "thinenabled": "on",
            "thinstep": 8
          }
        },
        {
          "name": "comment1",
          "type": "COMP:annotate",
          "parameters": {
            "pageindex": 3,
            "utility": "on",
            "includeinorder": "on"
          }
        },
        {
          "name": "comment2",
          "type": "COMP:annotate",
          "parameters": {
            "pageindex": 3,
            "utility": "on",
            "includeinorder": "on"
          }
        },
        {
          "name": "pointfilein1",
          "type": "POP:pointfilein",
          "parameters": {
            "attr0fields": "\"r y\"",
            "attr0name": "Boo"
          }
        },
        {
          "name": "pointfilein2",
          "type": "POP:pointfilein",
          "parameters": {}
        },
        {
          "name": "pointfilein3",
          "type": "POP:pointfilein",
          "parameters": {
            "pageindex": 1,
            "thinrangelength": 1000,
            "thinstep": 8
          }
        },
        {
          "name": "pointfilein4",
          "type": "POP:pointfilein",
          "parameters": {
            "positionfields": "\"X Y Z\"",
            "normalfields": "\"Nx Ny Nz\""
          }
        }
      ],
      "connections": [
        {
          "from": "pointfilein2",
          "to": "delete1",
          "to_input": "0"
        }
      ],
      "network_pattern": {
        "operator_count": 8,
        "connection_count": 1,
        "operator_types": {
          "DAT:text": 1,
          "POP:delete": 1,
          "COMP:annotate": 2,
          "POP:pointfilein": 4
        },
        "has_parallel_paths": false,
        "has_feedback_loops": false,
        "max_chain_length": 2
      }
    }
  ]
}