{
  "source_file": "C:\\TD_Projects\\td_builder_workspace\\output\\lossless\\websocketDAT_lossless.json",
  "operator_type": "websocketDAT",
  "examples": [
    {
      "name": "example1",
      "description": "",
      "operators": [
        {
          "name": "runMe",
          "type": "DAT:text",
          "parameters": {
            "defaultreadencoding": "cp1252",
            "language": "python"
          }
        },
        {
          "name": "readMe",
          "type": "DAT:text",
          "parameters": {
            "defaultreadencoding": "cp1252",
            "language": "text",
            "wordwrap": "on"
          }
        },
        {
          "name": "results",
          "type": "DAT:fifo",
          "parameters": {
            "callbacks": "fifo1_callbacks",
            "maxlines": 20,
            "language": "text"
          }
        },
        {
          "name": "websocket1",
          "type": "DAT:websocket",
          "parameters": {
            "netaddress": "ws://echo.websocket.events/",
            "callbacks": "websocket2_callbacks",
            "language": "text"
          }
        },
        {
          "name": "fifo1_callbacks",
          "type": "DAT:text",
          "parameters": {
            "language": "python"
          }
        },
        {
          "name": "websocket2_callbacks",
          "type": "DAT:text",
          "parameters": {
            "language": "python"
          }
        }
      ],
      "connections": [],
      "network_pattern": {
        "operator_count": 6,
        "connection_count": 0,
        "operator_types": {
          "DAT:text": 4,
          "DAT:fifo": 1,
          "DAT:websocket": 1
        },
        "has_parallel_paths": false,
        "has_feedback_loops": false,
        "max_chain_length": 1
      }
    }
  ]
}