{
  "source_file": "C:\\TD_Projects\\kb_pipeline\\data\\snippets\\lossless_pop\\linedividePOP_lossless.json",
  "operator_type": "linedividePOP",
  "examples": [
    {
      "name": "example1",
      "description": "",
      "operators": [
        {
          "name": "line24",
          "type": "POP:line",
          "parameters": {
            "pageindex": 1,
            "interpmethod": "cardinal",
            "attr0name": "color",
            "divs": 8,
            "addctrlpointattr": "on"
          }
        },
        {
          "name": "line26",
          "type": "POP:line",
          "parameters": {
            "pageindex": 1,
            "interpmethod": "cubicbeziertang",
            "attr0name": "color"
          }
        },
        {
          "name": "line27",
          "type": "POP:line",
          "parameters": {
            "pageindex": 1,
            "interpmethod": "cubicbeziertang",
            "attr0name": "color",
            "output": "ctrlpoints"
          }
        },
        {
          "name": "line28",
          "type": "POP:line",
          "parameters": {
            "pageindex": 1,
            "interpmethod": "cardinal",
            "attr0name": "color",
            "output": "ctrlpoints",
            "divs": 8
          }
        },
        {
          "name": "popto1",
          "type": "DAT:popto",
          "parameters": {
            "pop": "line24"
          }
        },
        {
          "name": "popto4",
          "type": "DAT:popto",
          "parameters": {
            "pop": "line27"
          }
        },
        {
          "name": "popto6",
          "type": "CHOP:popto",
          "parameters": {
            "pop": "linedivide3",
            "nameformat": "basic",
            "attribscope": "*"
          }
        },
        {
          "name": "popto7",
          "type": "DAT:popto",
          "parameters": {
            "pop": "linedivide3"
          }
        },
        {
          "name": "readMe",
          "type": "DAT:text",
          "parameters": {
            "defaultreadencoding": "cp1252",
            "language": "text",
            "wordwrap": "on"
          }
        },
        {
          "name": "circle1",
          "type": "POP:circle",
          "parameters": {
            "divs": 7
          }
        },
        {
          "name": "annotate3",
          "type": "COMP:annotate",
          "parameters": {
            "pageindex": 3,
            "includeinorder": "on"
          }
        },
        {
          "name": "popViewer",
          "type": "COMP:container",
          "parameters": {
            "pageindex": 11,
            "w": 1280,
            "h": 720,
            "topsmoothness": "usetop",
            "drop": "usecallbacks",
            "ext0object": "op('./ViewerExt').module.ViewerExt(me)",
            "ext0name": "ViewerExt",
            "ext0promote": "on",
            "ext1object": "\"\"",
            "ext1name": "\"\"",
            "iop1shortcut": "\"\"",
            "iop1op": "\"\""
          }
        },
        {
          "name": "annotate10",
          "type": "COMP:annotate",
          "parameters": {
            "pageindex": 3,
            "includeinorder": "on"
          }
        },
        {
          "name": "annotate12",
          "type": "COMP:annotate",
          "parameters": {
            "pageindex": 3,
            "includeinorder": "on"
          }
        },
        {
          "name": "annotate13",
          "type": "COMP:annotate",
          "parameters": {
            "pageindex": 3,
            "includeinorder": "on"
          }
        },
        {
          "name": "attribute2",
          "type": "POP:attribute",
          "parameters": {
            "attr0customname": "bds",
            "ren0from": "Tex",
            "ren0to": "ff",
            "dup0name": "N",
            "dup0new": "Rtss"
          }
        },
        {
          "name": "linedivide3",
          "type": "POP:linedivide",
          "parameters": {
            "pageindex": 1,
            "divs": 8,
            "addctrlpointattr": "on",
            "interpmethodpersegment": "on",
            "weightattr": "\"\"",
            "taninattr": "\"\"",
            "tanoutattr": "\"\"",
            "taninconstattr": "\"\""
          }
        },
        {
          "name": "linedivide6",
          "type": "POP:linedivide",
          "parameters": {
            "divs": 9,
            "maxdist": 0.16,
            "weightattr": "\"\"",
            "tension": 0.16
          }
        },
        {
          "name": "linedivide7",
          "type": "POP:linedivide",
          "parameters": {
            "pageindex": 2,
            "divmethod": "dist",
            "divs": 66,
            "maxdist": 0.05,
            "maxverts": 472,
            "interpmethod": "cardinal",
            "weightattr": "\"\"",
            "tension": 0.45,
            "resamplemethod": "linestrip",
            "resampledivs": 200
          }
        },
        {
          "name": "linedivide9",
          "type": "POP:linedivide",
          "parameters": {
            "pageindex": 1,
            "divs": 40,
            "interpmethodpersegment": "on",
            "weightattr": "\"\""
          }
        },
        {
          "name": "linedivide_weight",
          "type": "POP:linedivide",
          "parameters": {
            "pageindex": 1,
            "divs": 17,
            "interpmethod": "cardinal",
            "useweight": "on"
          }
        },
        {
          "name": "line_playWithWeights",
          "type": "POP:line",
          "parameters": {
            "pageindex": 1,
            "interpmethod": "cardinal",
            "enableweights": "on",
            "enabletangent": "on",
            "closed": "on",
            "attr0numcomps": 3,
            "output": "ctrlpoints"
          }
        }
      ],
      "connections": [
        {
          "from": "circle1",
          "to": "attribute2",
          "to_input": "0"
        },
        {
          "from": "line28",
          "to": "linedivide3",
          "to_input": "0"
        },
        {
          "from": "attribute2",
          "to": "linedivide6",
          "to_input": "0"
        },
        {
          "from": "attribute2",
          "to": "linedivide7",
          "to_input": "0"
        },
        {
          "from": "line27",
          "to": "linedivide9",
          "to_input": "0"
        },
        {
          "from": "line_playWithWeights",
          "to": "linedivide_weight",
          "to_input": "0"
        }
      ],
      "network_pattern": {
        "operator_count": 22,
        "connection_count": 6,
        "operator_types": {
          "POP:line": 5,
          "DAT:popto": 3,
          "CHOP:popto": 1,
          "DAT:text": 1,
          "POP:circle": 1,
          "COMP:annotate": 4,
          "COMP:container": 1,
          "POP:attribute": 1,
          "POP:linedivide": 5
        },
        "has_parallel_paths": true,
        "has_feedback_loops": false,
        "max_chain_length": 3
      }
    },
    {
      "name": "example2",
      "description": "",
      "operators": [
        {
          "name": "popto5",
          "type": "CHOP:popto",
          "parameters": {
            "pop": "linedivide1",
            "nameformat": "basic",
            "attribscope": "*",
            "renscope": "\"tx ty tz\""
          }
        },
        {
          "name": "readMe",
          "type": "DAT:text",
          "parameters": {
            "defaultreadencoding": "cp1252",
            "language": "text",
            "wordwrap": "on"
          }
        },
        {
          "name": "line111",
          "type": "POP:line",
          "parameters": {
            "attr0name": "color"
          }
        },
        {
          "name": "line155",
          "type": "POP:line",
          "parameters": {
            "pageindex": 1,
            "interpmethod": "cardinal",
            "tension": 1.5,
            "enableweights": "on",
            "closed": "on",
            "attr0customname": "Hello",
            "attr0value3": 1,
            "divmethod": "defpersegment",
            "dist": 0.19,
            "resamplemethod": "linestrip",
            "resampledivs": 120,
            "resampledist": 0.03,
            "resamplemaxverts": 782,
            "maxtries": 79
          }
        },
        {
          "name": "line166",
          "type": "POP:line",
          "parameters": {
            "interpmethod": "cardinal",
            "tension": 1.5,
            "enableweights": "on",
            "closed": "on",
            "attr0customname": "Hello",
            "attr0value3": 1,
            "output": "ctrlpoints",
            "divmethod": "defpersegment"
          }
        },
        {
          "name": "comment1",
          "type": "COMP:annotate",
          "parameters": {
            "pageindex": 3,
            "utility": "on",
            "includeinorder": "on"
          }
        },
        {
          "name": "annotate11",
          "type": "COMP:annotate",
          "parameters": {
            "pageindex": 3,
            "includeinorder": "on"
          }
        },
        {
          "name": "linedivide1",
          "type": "POP:linedivide",
          "parameters": {
            "divs": 2,
            "interpmethod": "cardinal",
            "weightattr": "\"\""
          }
        },
        {
          "name": "linedivide2",
          "type": "POP:linedivide",
          "parameters": {
            "interpmethod": "cardinal"
          }
        },
        {
          "name": "pattern_random",
          "type": "POP:pattern",
          "parameters": {
            "parsize": 1,
            "seed": 7.79,
            "outputattrscope": "rand"
          }
        }
      ],
      "connections": [
        {
          "from": "line155",
          "to": "linedivide1",
          "to_input": "0"
        },
        {
          "from": "line166",
          "to": "linedivide2",
          "to_input": "0"
        },
        {
          "from": "line111",
          "to": "pattern_random",
          "to_input": "0"
        }
      ],
      "network_pattern": {
        "operator_count": 10,
        "connection_count": 3,
        "operator_types": {
          "CHOP:popto": 1,
          "DAT:text": 1,
          "POP:line": 3,
          "COMP:annotate": 2,
          "POP:linedivide": 2,
          "POP:pattern": 1
        },
        "has_parallel_paths": false,
        "has_feedback_loops": false,
        "max_chain_length": 2
      }
    }
  ]
}