{
  "source_file": "C:\\TD_Projects\\td_builder_workspace\\output\\lossless\\selectCOMP_lossless.json",
  "operator_type": "selectCOMP",
  "examples": [
    {
      "name": "example1",
      "description": "",
      "operators": [
        {
          "name": "panel1",
          "type": "COMP:container",
          "parameters": {
            "w": 100,
            "h": 100,
            "top": "./text1",
            "topsmoothness": "mipmap"
          }
        },
        {
          "name": "panel2",
          "type": "COMP:container",
          "parameters": {
            "w": 90,
            "h": 90,
            "top": "./text1",
            "topsmoothness": "mipmap"
          }
        },
        {
          "name": "panel3",
          "type": "COMP:container",
          "parameters": {
            "w": 80,
            "h": 80,
            "top": "./text1",
            "topsmoothness": "mipmap"
          }
        },
        {
          "name": "readMe",
          "type": "DAT:text",
          "parameters": {
            "pageindex": 1,
            "defaultreadencoding": "cp1252",
            "language": "text",
            "wordwrap": "on"
          }
        },
        {
          "name": "select1",
          "type": "COMP:select",
          "parameters": {
            "pageindex": 4,
            "w": 100,
            "h": 100,
            "topsmoothness": "mipmap"
          }
        },
        {
          "name": "select2",
          "type": "COMP:select",
          "parameters": {
            "pageindex": 4,
            "w": 100,
            "h": 100,
            "topsmoothness": "mipmap"
          }
        },
        {
          "name": "select3",
          "type": "COMP:select",
          "parameters": {
            "topsmoothness": "mipmap"
          }
        },
        {
          "name": "constant1",
          "type": "CHOP:constant",
          "parameters": {
            "const0value": 1
          }
        }
      ],
      "connections": [],
      "network_pattern": {
        "operator_count": 8,
        "connection_count": 0,
        "operator_types": {
          "COMP:container": 3,
          "DAT:text": 1,
          "COMP:select": 3,
          "CHOP:constant": 1
        },
        "has_parallel_paths": false,
        "has_feedback_loops": false,
        "max_chain_length": 1
      }
    }
  ]
}